stackscrape/__init__.py
stackscrape/__main__.py
stackscrape/stackscrape.py
stackscrape-0.3.dist-info/entry_points.txt
stackscrape-0.3.dist-info/LICENSE
stackscrape-0.3.dist-info/WHEEL
stackscrape-0.3.dist-info/METADATA
stackscrape-0.3.dist-info/RECORD
