Metadata-Version: 2.1
Name: stackscrape
Version: 0.3
Summary: stackscrape.
Author-email: Graham Wheeler <graham@grahamwheeler.com>
Classifier: Intended Audience :: Developers
Classifier: License :: OSI Approved :: MIT License
Classifier: Programming Language :: Python :: 3
Classifier: Topic :: Software Development :: Libraries :: Python Modules
Requires-Dist: flit_core >=3.7.1
Requires-Dist: docopt
Requires-Dist: stackapi
Project-URL: Source, https://github.com/gramster/stackscrape
